logagg/__init__.py
logagg/collector.py
logagg/command.py
logagg/formatters.py
logagg/forwarder.py
logagg/forwarders.py
logagg/nsqsender.py
logagg/util.py
logagg-0.3.5.dist-info/LICENSE
logagg-0.3.5.dist-info/METADATA
logagg-0.3.5.dist-info/WHEEL
logagg-0.3.5.dist-info/dependency_links.txt
logagg-0.3.5.dist-info/entry_points.txt
logagg-0.3.5.dist-info/top_level.txt
logagg-0.3.5.dist-info/RECORD
