Metadata-Version: 2.1
Name: logagg
Version: 0.3.5
Summary: logs aggregation framework
Home-page: https://github.com/deep-compute/logagg
Author: Deep Compute, LLC
Author-email: contact@deepcompute.com
License: MIT
Keywords: logagg
Platform: UNKNOWN
Classifier: Environment :: Console
Classifier: Intended Audience :: Developers
Classifier: Natural Language :: English
Classifier: Programming Language :: Python
Classifier: Programming Language :: Python :: 2.7
Classifier: Operating System :: OS Independent
Classifier: License :: OSI Approved :: MIT License
Requires-Dist: basescript (==0.2.0)
Requires-Dist: pymongo (==3.6.0)
Requires-Dist: nsq-py (==0.1.10)
Requires-Dist: influxdb (==4.1.1)
Requires-Dist: deeputil (==0.2.5)
Requires-Dist: ujson (==1.35)
